ccparser/__init__.py
ccparser/cli.py
ccparser/formatter.py
ccparser/generator.py
ccparser/parser.py
ccparser/utils.py
ccparser/validator.py
ccparser-2.0.1.dist-info/licenses/LICENSE
ccparser-2.0.1.dist-info/METADATA
ccparser-2.0.1.dist-info/WHEEL
ccparser-2.0.1.dist-info/entry_points.txt
ccparser-2.0.1.dist-info/top_level.txt
ccparser-2.0.1.dist-info/RECORD
