Metadata-Version: 2.4
Name: CCParser
Version: 2.0.1
Summary: A powerful library for credit card parsing, validation, and formatting
Author-email: Vihanga Indusara <vihangadev@gmail.com>
Maintainer-email: Vihanga Indusara <vihangadev@gmail.com>
License: MIT
Project-URL: Homepage, https://github.com/VihangaDev/CCParser
Project-URL: Documentation, https://github.com/VihangaDev/CCParser#readme
Project-URL: Repository, https://github.com/VihangaDev/CCParser.git
Project-URL: Issues, https://github.com/VihangaDev/CCParser/issues
Project-URL: Changelog, https://github.com/VihangaDev/CCParser/blob/master/CHANGELOG.md
Keywords: credit-card,parser,validation,luhn,payment,visa,mastercard,amex,formatting
Classifier: Development Status :: 5 - Production/Stable
Classifier: Intended Audience :: Developers
Classifier: License :: OSI Approved :: MIT License
Classifier: Operating System :: OS Independent
Classifier: Programming Language :: Python :: 3
Classifier: Programming Language :: Python :: 3.10
Classifier: Programming Language :: Python :: 3.11
Classifier: Programming Language :: Python :: 3.12
Classifier: Programming Language :: Python :: 3.13
Classifier: Topic :: Software Development :: Libraries :: Python Modules
Classifier: Topic :: Office/Business :: Financial
Classifier: Typing :: Typed
Requires-Python: >=3.10
License-File: LICENSE
Provides-Extra: api
Requires-Dist: requests>=2.25.0; extra == "api"
Provides-Extra: dev
Requires-Dist: pytest>=7.0.0; extra == "dev"
Requires-Dist: pytest-cov>=4.0.0; extra == "dev"
Requires-Dist: flake8>=6.0.0; extra == "dev"
Requires-Dist: mypy>=1.0.0; extra == "dev"
Requires-Dist: black>=23.0.0; extra == "dev"
Requires-Dist: isort>=5.12.0; extra == "dev"
Provides-Extra: all
Requires-Dist: CCParser[api,dev]; extra == "all"
Dynamic: license-file
